{
  "version": "7",
  "dialect": "postgresql",
  "entries": [
    {
      "idx": 0,
      "version": "7",
      "when": 1775440546407,
      "tag": "0000_init",
      "breakpoints": true
    },
    {
      "idx": 1,
      "version": "7",
      "when": 1775440902987,
      "tag": "0001_users_files_roles",
      "breakpoints": true
    },
    {
      "idx": 2,
      "version": "7",
      "when": 1775443000458,
      "tag": "0002_work_schedule_types",
      "breakpoints": true
    },
    {
      "idx": 3,
      "version": "7",
      "when": 1775444000000,
      "tag": "0003_schedule_period_kind",
      "breakpoints": true
    },
    {
      "idx": 4,
      "version": "7",
      "when": 1775445000000,
      "tag": "0004_staff_members",
      "breakpoints": true
    },
    {
      "idx": 5,
      "version": "7",
      "when": 1775446000000,
      "tag": "0005_citizen_feedback",
      "breakpoints": true
    },
    {
      "idx": 6,
      "version": "7",
      "when": 1775447000000,
      "tag": "0006_citizen_accounts",
      "breakpoints": true
    },
    {
      "idx": 7,
      "version": "7",
      "when": 1775448000000,
      "tag": "0007_citizen_feedback_account_fk",
      "breakpoints": true
    },
    {
      "idx": 8,
      "version": "7",
      "when": 1775449000000,
      "tag": "0008_citizen_accounts_id_pk",
      "breakpoints": true
    },
    {
      "idx": 9,
      "version": "7",
      "when": 1775450000000,
      "tag": "0009_citizen_feedback_submitter_from_account",
      "breakpoints": true
    },
    {
      "idx": 10,
      "version": "7",
      "when": 1775451000000,
      "tag": "0010_citizen_feedback_answered_by",
      "breakpoints": true
    },
    {
      "idx": 11,
      "version": "7",
      "when": 1775452000000,
      "tag": "0011_citizen_feedback_staff_reply",
      "breakpoints": true
    },
    {
      "idx": 12,
      "version": "7",
      "when": 1775453000000,
      "tag": "0012_citizen_feedback_hidden_from_app",
      "breakpoints": true
    },
    {
      "idx": 13,
      "version": "7",
      "when": 1775454000000,
      "tag": "0013_public_service_hotlines",
      "breakpoints": true
    },
    {
      "idx": 14,
      "version": "7",
      "when": 1775455000000,
      "tag": "0014_news_articles",
      "breakpoints": true
    },
    {
      "idx": 15,
      "version": "7",
      "when": 1775456000000,
      "tag": "0015_news_article_categories",
      "breakpoints": true
    },
    {
      "idx": 16,
      "version": "7",
      "when": 1775457000000,
      "tag": "0016_news_articles_category_required",
      "breakpoints": true
    },
    {
      "idx": 17,
      "version": "7",
      "when": 1775458000000,
      "tag": "0017_staff_member_ratings",
      "breakpoints": true
    },
    {
      "idx": 18,
      "version": "7",
      "when": 1775459000000,
      "tag": "0018_app_mobile_config",
      "breakpoints": true
    },
    {
      "idx": 19,
      "version": "7",
      "when": 1775540000000,
      "tag": "0019_citizen_accounts_active",
      "breakpoints": true
    },
    {
      "idx": 20,
      "version": "7",
      "when": 1775541000000,
      "tag": "0020_app_home_banner_placement",
      "breakpoints": true
    },
    {
      "idx": 21,
      "version": "7",
      "when": 1775542000000,
      "tag": "0021_file_category_app_home_icon",
      "breakpoints": true
    },
    {
      "idx": 22,
      "version": "7",
      "when": 1775543000000,
      "tag": "0022_app_mobile_home_items_icon_file",
      "breakpoints": true
    },
    {
      "idx": 23,
      "version": "7",
      "when": 1776086271118,
      "tag": "0023_calm_the_phantom",
      "breakpoints": true
    },
    {
      "idx": 24,
      "version": "7",
      "when": 1776087200000,
      "tag": "0024_app_mobile_shell_tabs",
      "breakpoints": true
    },
    {
      "idx": 25,
      "version": "7",
      "when": 1776088200000,
      "tag": "0025_app_mobile_home_banner_cta",
      "breakpoints": true
    },
    {
      "idx": 26,
      "version": "7",
      "when": 1776089200000,
      "tag": "0026_app_mobile_home_banner_categories",
      "breakpoints": true
    },
    {
      "idx": 27,
      "version": "7",
      "when": 1776090200000,
      "tag": "0027_app_mobile_home_banner_section_link",
      "breakpoints": true
    },
    {
      "idx": 28,
      "version": "7",
      "when": 1776847798967,
      "tag": "0028_solid_jack_flag",
      "breakpoints": true
    },
    {
      "idx": 29,
      "version": "7",
      "when": 1776850000000,
      "tag": "0029_app_mobile_home_items_default_favorite",
      "breakpoints": true
    }
  ]
}